bkpaas_auth/__init__.py
bkpaas_auth/apps.py
bkpaas_auth/backends.py
bkpaas_auth/conf.py
bkpaas_auth/core/__init__.py
bkpaas_auth/core/algorithms.py
bkpaas_auth/core/constants.py
bkpaas_auth/core/encoder.py
bkpaas_auth/core/exceptions.py
bkpaas_auth/core/http.py
bkpaas_auth/core/plugins.py
bkpaas_auth/core/services.py
bkpaas_auth/core/token.py
bkpaas_auth/core/user_info.py
bkpaas_auth/core/utils.py
bkpaas_auth/middlewares.py
bkpaas_auth/models.py
bkpaas_auth/monkey.py
bkpaas_auth/utils.py
bkpaas_auth-3.1.2.dist-info/METADATA
bkpaas_auth-3.1.2.dist-info/WHEEL
bkpaas_auth-3.1.2.dist-info/RECORD
