Metadata-Version: 2.1
Name: bkpaas-auth
Version: 3.1.2
Summary: User authentication django app for blueking internal projects
License: MIT
Author: blueking
Author-email: blueking@tencent.com
Requires-Python: >=3.8,<4.0
Classifier: License :: OSI Approved :: MIT License
Classifier: Programming Language :: Python :: 3
Classifier: Programming Language :: Python :: 3.8
Classifier: Programming Language :: Python :: 3.9
Classifier: Programming Language :: Python :: 3.10
Classifier: Programming Language :: Python :: 3.11
Requires-Dist: django (>=4.2,<5.0)
Requires-Dist: requests
Requires-Dist: six
